sqlalchemy_query_manager/__init__.py
sqlalchemy_query_manager/consts.py
sqlalchemy_query_manager/core/__init__.py
sqlalchemy_query_manager/core/base.py
sqlalchemy_query_manager/core/helpers.py
sqlalchemy_query_manager/core/transaction_context_manager.py
sqlalchemy_query_manager/core/utils.py
sqlalchemy_query_manager-0.4.4.dist-info/METADATA
sqlalchemy_query_manager-0.4.4.dist-info/WHEEL
sqlalchemy_query_manager-0.4.4.dist-info/RECORD
