Metadata-Version: 2.1
Name: sqlalchemy-query-manager
Version: 0.4.4
Summary: 
Author: ViAchKoN
Requires-Python: >=3.8.1,<4.0.0
Classifier: Programming Language :: Python :: 3
Classifier: Programming Language :: Python :: 3.9
Classifier: Programming Language :: Python :: 3.10
Classifier: Programming Language :: Python :: 3.11
Classifier: Programming Language :: Python :: 3.12
Requires-Dist: dataclass-sqlalchemy-mixins (>=0.3.4,<0.4.0)
Requires-Dist: sqlalchemy (>=1.4.2)
